gitlab_bulkcheckout
