Metadata-Version: 2.1
Name: gitlab-bulkcheckout
Version: 0.22.0
Summary: Command line utility for handle multiply git projects
Home-page: https://github.com/nolte/gitlab-bulkcheckout
Author: nolte
Author-email: nolte07@gmail.com
License: Apache Software License 2.0
Keywords: gitlab_bulkcheckout
Platform: UNKNOWN
Classifier: Development Status :: 2 - Pre-Alpha
Classifier: Intended Audience :: Developers
Classifier: License :: OSI Approved :: Apache Software License
Classifier: Natural Language :: German
Classifier: Programming Language :: Python :: 3.5
Classifier: Programming Language :: Python :: 3.6
Classifier: Programming Language :: Python :: 3.7
